setuputils.py
setuputils_build.py
setuputils3-2.2.dist-info/METADATA
setuputils3-2.2.dist-info/WHEEL
setuputils3-2.2.dist-info/top_level.txt
setuputils3-2.2.dist-info/RECORD
