Metadata-Version: 2.1
Name: setuputils3
Version: 2.2
Summary: A utility module to automate building setup configuration files.
Home-page: http://pypi.org/project/setuputils3
Author: Peter A. Donis
Author-email: peterdonis@alum.mit.edu
License: PSF
Classifier: Development Status :: 5 - Production/Stable
Classifier: Environment :: Console
Classifier: Intended Audience :: Developers
Classifier: Intended Audience :: System Administrators
Classifier: License :: OSI Approved :: Python Software Foundation License
Classifier: Operating System :: OS Independent
Classifier: Programming Language :: Python :: 3
Classifier: Topic :: Software Development :: Libraries :: Python Modules
Classifier: Topic :: System :: Systems Administration
Classifier: Topic :: Utilities
